Workbook

Sheet Umsatzprognose
A1: AlltagsEngel UG - Frankfurt am Main
A2: Umsatzprognose (Revenue Forecast) - 5 Jahre
B4: M1 | C4: M2 | D4: M3 | E4: M4 | F4: M5 | G4: M6 | H4: M7 | I4: M8 | J4: M9 | K4: M10 | L4: M11 | M4: M12 | N4: Jahr 2 | O4: Jahr 3 | P4: Jahr 4 | Q4: Jahr 5
A5: Aktive Nutzer | B5: 20 | C5: 63 | D5: 107 | E5: 150 | F5: 194 | G5: 238 | H5: 281 | I5: 325 | J5: 369 | K5: 412 | L5: 456 | M5: 500 | N5: 2500 | O5: 10000 | P5: 35000 | Q5: 75000
A6: Registrierte Engel | B6: 5 | C6: 9 | D6: 13 | E6: 17 | F6: 21 | G6: 25 | H6: 29 | I6: 33 | J6: 37 | K6: 41 | L6: 45 | M6: 50 | N6: 150 | O6: 500 | P6: 2000 | Q6: 5000
A7: Buchungen/Monat | B7: 15 | C7: 50 | D7: 85 | E7: 120 | F7: 155 | G7: 190 | H7: 225 | I7: 260 | J7: 295 | K7: 330 | L7: 365 | M7: 400 | N7: 8000 | O7: 40000 | P7: 180000 | Q7: 450000
A8: Ø Buchungswert (€) | B8: 40 | C8: 40 | D8: 40 | E8: 40 | F8: 40 | G8: 40 | H8: 40 | I8: 40 | J8: 40 | K8: 40 | L8: 40 | M8: 40 | N8: 40 | O8: 40 | P8: 40 | Q8: 40
A9: Umsatz Provisionen (18%) | B9: =(B7*B8*0.18) | C9: =(C7*C8*0.18) | D9: =(D7*D8*0.18) | E9: =(E7*E8*0.18) | F9: =(F7*F8*0.18) | G9: =(G7*G8*0.18) | H9: =(H7*H8*0.18) | I9: =(I7*I8*0.18) | ... Q9: =(Q7*Q8*0.18)
A10: Premium-Abos Engel (€9,99/Monat) | B10: =(B6*0.3*9.99) | C10: =(C6*0.3*9.99) | D10: =(D6*0.3*9.99) | E10: =(E6*0.3*9.99) | F10: =(F6*0.3*9.99) | G10: =(G6*0.3*9.99) | H10: =(H6*0.3*9.99) | I10: =(I6*0.3*9.99) | ... Q10: =(Q6*0.3*9.99)
A11: Gesamtumsatz | B11: =B9+B10 | C11: =C9+C10 | D11: =D9+D10 | E11: =E9+E10 | F11: =F9+F10 | G11: =G9+G10 | H11: =H9+H10 | I11: =I9+I10 | ... Q11: =Q9+Q10

Sheet Gewinn-und-Verlust
A1: AlltagsEngel UG - Gewinn- und Verlustrechnung
A3: Position | B3: Jahr 1 | C3: Jahr 2 | D3: Jahr 3 | E3: Jahr 4 | F3: Jahr 5
A4: UMSATZ
A5: Provisionseinnahmen | B5: =SUM(Umsatzprognose!C9:M9) | C5: =Umsatzprognose!O9 | D5: =Umsatzprognose!P9 | E5: =Umsatzprognose!Q9 | F5: =Umsatzprognose!R9
A6: Premium-Abonnements | B6: =SUM(Umsatzprognose!C10:M10) | C6: =Umsatzprognose!O10 | D6: =Umsatzprognose!P10 | E6: =Umsatzprognose!Q10 | F6: =Umsatzprognose!R10
A7: Gesamtumsatz | B7: =B5+B6 | C7: =C5+C6 | D7: =D5+D6 | E7: =E5+E6 | F7: =F5+F6
A9: KOSTEN
A10: Personalkosten (Brutto) | B10: 374400 | C10: =B10*1.20 | D10: =C10*1.20 | E10: =D10*1.20 | F10: =E10*1.20
A11: Büromiete | B11: 7200 | C11: =B11*1.10 | D11: =C11*1.10 | E11: =D11*1.10 | F11: =E11*1.10
A12: Fahrzeugkosten | B12: 12000 | C12: =B12 | D12: =C12 | E12: =D12 | F12: =E12
A13: Software & Infrastruktur | B13: 2400 | C13: =B13*1.15 | D13: =C13*1.15 | E13: =D13*1.15 | F13: =E13*1.15
A14: Marketing & Werbung | B14: 10200 | C14: =B14*1.50 | D14: =C14*1.50 | E14: =D14*1.50 | F14: =E14*1.50
A15: Versicherungen | B15: 3600 | C15: =B15*1.25 | D15: =C15*1.25 | E15: =D15*1.25 | F15: =E15*1.25
A16: Steuerberater | B16: 4800 | C16: =B16 | D16: =C16 | E16: =D16 | F16: =E16
A17: Sonstige Betriebskosten | B17: 3000 | C17: =B17*1.10 | D17: =C17*1.10 | E17: =D17*1.10 | F17: =E17*1.10
A18: Gesamtkosten | B18: =SUM(B10:B17) | C18: =SUM(C10:C17) | D18: =SUM(D10:D17) | E18: =SUM(E10:E17) | F18: =SUM(F10:F17)
A20: ERGEBNIS
A21: EBITDA | B21: =B7-B18 | C21: =C7-C18 | D21: =D7-D18 | E21: =E7-E18 | F21: =F7-F18
A22: EBITDA-Marge (%) | B22: =B21/B7 | C22: =C21/C7 | D22: =D21/D7 | E22: =E21/E7 | F22: =F21/F7

Sheet Kennzahlen
A1: AlltagsEngel UG - Key Metrics Dashboard
A3: Metrik | B3: Wert | C3: Einheit
A4: Monatliche Burn-Rate (Jahr 1) | B4: =Gewinn-und-Verlust!B18/12 | C4: €
A5: Runway bei €500K Seed | B5: =500000/B4 | C5: Monate
A6: Break-Even Buchungen/Monat | B6: =(Gewinn-und-Verlust!B18)/40/0.18 | C6: Buchungen
A7: CAC (Customer Acquisition Cost) | B7: 20 | C7: €
A8: LTV (Lifetime Value) | B8: 500 | C8: €
A9: LTV/CAC Ratio | B9: =B7/B6 | C9: Faktor
A10: Payback Period | B10: =(B6)/(Gewinn-und-Verlust!B5/12) | C10: Monate
A11: Monthly Recurring Revenue (MRR) Y1 | B11: =SUM(Umsatzprognose!C11:M11)/12 | C11: €
