Workbook

Sheet Übersicht
B2: AlltagsEngel
B3: Finanzmodell 2026–2028
B4: 3-Jahres-Plan · Pre-Seed · Frankfurt am Main · Vertraulich
B6: Key Financials
C8: 2026 | D8: 2027 | E8: 2028 | F8: Summe
B10: Umsatz | C10: ='P&L'!C12 -> 833250 | D10: ='P&L'!D12 -> 4116825 | E10: ='P&L'!E12 -> 11153484 | F10: =SUM(C10:E10) -> 16103559
B11: EBITDA | C11: ='P&L'!C25 -> -637248.75 | D11: ='P&L'!D25 -> -708687.38 | E11: ='P&L'!E25 -> 40129.74 | F11: =SUM(C11:E11) -> -1305806.4
B12: Cash-Burn | C12: =Cashflow!C14 -> -723911.25 | D12: =Cashflow!D14 -> -932866.12 | E12: =Cashflow!E14 -> -391703.21 | F12: =SUM(C12:E12) -> -2048480.6
B13: Aktive Kunden (Ende) | C13: =Umsatz!C5 -> 500 | D13: =Umsatz!D5 -> 1750 | E13: =Umsatz!E5 -> 3740
B14: Aktive Engel (Ende) | C14: =Umsatz!C7 -> 63 | D14: =Umsatz!D7 -> 219 | E14: =Umsatz!E7 -> 468
B15: Buchungen / Jahr | C15: =Umsatz!C9 -> 18000 | D15: =Umsatz!D9 -> 87750 | E15: =Umsatz!E9 -> 230580 | F15: =SUM(C15:E15) -> 336330
B17: Finanzierung
B19: Kapitalbedarf (Pre-Seed) | C19: =Kapital!C7 -> 1000000
B20: Runway (Monate) | C20: =Kapital!C9 -> 16.576618
B21: Break-Even-Quartal | C21: Q2 2028
B22: LTV je Kunde | C22: =Annahmen!E34 -> 2296.56
B23: CAC je Kunde | C23: =Annahmen!E35 -> 250
B24: LTV:CAC-Verhältnis | C24: =C22/C23 -> 9.18624
B27: Farbkonventionen
B28: Blau = Annahme (Input)
B29: Schwarz = Formel
B30: Grün = Verweis auf Sheet
B31: Gelber Hintergrund = Schlüssel-Annahme

Sheet Annahmen
B2: Annahmen & Parameter
B3: Alle blauen Werte = Input-Zellen. Gelb = Schlüssel-Annahmen.
C5: 2026 | D5: 2027 | E5: 2028 | F5: Quelle / Begründung
B7: Kunden & Nachfrage
B8: Neukunden (brutto) | C8: 500 | D8: 1300 | E8: 2200 | F8: Frankfurt / +Köln Q2'27 / +Düsseldorf Q4'27
B9: Churn pro Jahr | C9: 0.08 | D9: 0.1 | E9: 0.12 | F9: Pflege-Dauer ~28 Monate (konservativ)
B10: Ø Buchungsstunden / Kunde / Monat | C10: 6 | D10: 6.5 | E10: 7 | F10: 1,5 Termine/Woche à 1h
B11: Ø Fahrten / Fahrtkunde / Monat | C11: 8 | D11: 8 | E11: 8 | F11: Dialyse 3x/Woche Hin+Zurück
B12: Anteil Kunden mit Fahrten | C12: 0.25 | D12: 0.28 | E12: 0.3 | F12: Schwerpflegebedürftige
B13: Anteil Kunden mit Pflegebox | C13: 0.4 | D13: 0.45 | E13: 0.5 | F13: Pflegegrad 1+, ProCare-Partnerschaft
B14: Anteil Premium-Abo | C14: 0.05 | D14: 0.08 | E14: 0.1 | F14: Familien mit persönlichem Care-Manager
B16: Preise & Margen
B17: Alltagshilfe Stundensatz (€/h, §45b) | C17: 32.5 | D17: 32.5 | E17: 33.5 | F17: Kassensatz §45b Hessen/NRW
B18: Engel-Vergütung (€/h) | C18: 25 | D18: 25 | E18: 26 | F18: Überdurchschnittlich, Differenzierung
B19: Marge Alltagshilfe (€/h) | C19: =C17-C18 -> 7.5 | D19: =D17-D18 -> 7.5 | E19: =E17-E18 -> 7.5 | F19: Kassensatz − Engel-Vergütung
B20: Fahrt Erstattung (€/Fahrt) | C20: 32 | D20: 32 | E20: 33 | F20: Ø einfache Fahrt Dialyse innerstädtisch
B21: Fahrer-Vergütung (€/Fahrt) | C21: 24 | D21: 24 | E21: 24.5 | F21: ~8 € AE-Marge je Fahrt
B22: Pflegebox Umsatz (€/Box, §40) | C22: 42 | D22: 42 | E22: 42 | F22: §40-Pauschale SGB XI (gesetzlich fix)
B23: Marge pro Box (€) | C23: 12 | D23: 12 | E23: 12 | F23: ProCare-Partnerschaft, COGS ~30 €
B24: Premium-Abo (€/Monat) | C24: 39 | D24: 39 | E24: 39 | F24: 29–49 € Range, Mittelwert
B26: Operative Kosten
B27: Gehälter / Jahr (€) | C27: 480000 | D27: 960000 | E27: 1560000 | F27: 6 FTE → 12 FTE → 20 FTE (inkl. LNK)
B28: Marketing / Jahr (€) | C28: 180000 | D28: 420000 | E28: 550000 | F28: Performance, Content, Ärzte-Empfehlungen
B29: Infrastruktur & Tools (€) | C29: 36000 | D29: 72000 | E29: 120000 | F29: Supabase, Vercel, Stripe, Sentry, Monitoring
B30: Recht, Compliance, Versicherung (€) | C30: 72000 | D30: 90000 | E30: 110000 | F30: §45a/§45b Zulassung, DSGVO-Audits
B31: Overhead & Sonstiges (€) | C31: 60000 | D31: 120000 | E31: 180000 | F31: Büro, Reisen, Legal, Buchhaltung
B33: Unit Economics
B34: LTV je Kunde (€) | C34: =((C19*C10 + (C20-C21)*C11*C12 + C23*C13 + C24*0.8*C14) * 28) -> 1886.08 | D34: =((D19*D10 + (D20-D21)*D11*D12 + D23*D13 + D24*0.8*D14) * 28) -> 2087.848 | E34: =((E19*E10 + (E20-E21)*E11*E12 + E23*E13 + E24*0.8*E14) * 28) -> 2296.56 | F34: Ø Lebensdauer 28 Monate × Bruttomarge/Monat
B35: CAC je Kunde (€) | C35: =C28/C8 -> 360 | D35: =D28/D8 -> 323.07692 | E35: =E28/E8 -> 250 | F35: Marketing / Neukunden
B36: LTV:CAC | C36: =C34/C35 -> 5.2391111 | D36: =D34/D35 -> 6.4623867 | E36: =E34/E35 -> 9.18624 | F36: Zielkorridor > 3x
B37: Payback-Periode (Monate) | C37: =C35/((C19*C10 + (C20-C21)*C11*C12 + C23*C13 + C24*0.8*C14)) -> 5.3444181 | D37: =D35/((D19*D10 + (D20-D21)*D11*D12 + D23*D13 + D24*0.8*D14)) -> 4.3327646 | E37: =E35/((E19*E10 + (E20-E21)*E11*E12 + E23*E13 + E24*0.8*E14)) -> 3.0480371 | F37: CAC / Bruttomarge pro Monat

Sheet Umsatz
B2: Umsatz-Projektion
B3: Kunden-Kohorten und vier Einnahmeströme
B4: Kunden (Anfang) | C4: 0 | D4: =C5 -> 500 | E4: =D5 -> 1750
B5: Kunden (Ende Jahr) | C5: =C4+Annahmen!C8-C4*Annahmen!C9 -> 500 | D5: =D4+Annahmen!D8-D4*Annahmen!D9 -> 1750 | E5: =E4+Annahmen!E8-E4*Annahmen!E9 -> 3740
B6: Ø Kunden im Jahr | C6: =(C4+C5)/2 -> 250 | D6: =(D4+D5)/2 -> 1125 | E6: =(E4+E5)/2 -> 2745
B7: Aktive Engel (Ende) | C7: =ROUNDUP(C5/8,0) -> 63 | D7: =ROUNDUP(D5/8,0) -> 219 | E7: =ROUNDUP(E5/8,0) -> 468
B8: Buchungen/Jahr = Ø Kunden × Stunden/Monat × 12
B9: Buchungen/Jahr | C9: =C6*Annahmen!C10*12 -> 18000 | D9: =D6*Annahmen!D10*12 -> 87750 | E9: =E6*Annahmen!E10*12 -> 230580
B11: Umsatz nach Einnahmestrom
B13: Stream 1: Alltagshilfe (§45b) | C13: =C9*Annahmen!C17 -> 585000 | D13: =D9*Annahmen!D17 -> 2851875 | E13: =E9*Annahmen!E17 -> 7724430
B14: Stream 2: Krankenfahrten | C14: =C6*Annahmen!C12*Annahmen!C11*12*Annahmen!C20 -> 192000 | D14: =D6*Annahmen!D12*Annahmen!D11*12*Annahmen!D20 -> 967680 | E14: =E6*Annahmen!E12*Annahmen!E11*12*Annahmen!E20 -> 2608848
B15: Stream 3: Pflegeboxen (§40) | C15: =C6*Annahmen!C13*Annahmen!C22*12 -> 50400 | D15: =D6*Annahmen!D13*Annahmen!D22*12 -> 255150 | E15: =E6*Annahmen!E13*Annahmen!E22*12 -> 691740
B16: Stream 4: Premium-Abo | C16: =C6*Annahmen!C14*Annahmen!C24*12 -> 5850 | D16: =D6*Annahmen!D14*Annahmen!D24*12 -> 42120 | E16: =E6*Annahmen!E14*Annahmen!E24*12 -> 128466
B18: Gesamt-Umsatz | C18: =SUM(C13:C16) -> 833250 | D18: =SUM(D13:D16) -> 4116825 | E18: =SUM(E13:E16) -> 11153484
B20: Umsatz-Mix
B21: Alltagshilfe | C21: =C13/C18 -> 0.70207021 | D21: =D13/D18 -> 0.69273651 | E21: =E13/E18 -> 0.69255759
B22: Krankenfahrten | C22: =C14/C18 -> 0.23042304 | D22: =D14/D18 -> 0.23505493 | E22: =E14/E18 -> 0.23390431
B23: Pflegeboxen | C23: =C15/C18 -> 0.060486049 | D23: =D15/D18 -> 0.061977373 | E23: =E15/E18 -> 0.062020083
B24: Premium-Abo | C24: =C16/C18 -> 0.0070207021 | D24: =D16/D18 -> 0.010231185 | E24: =E16/E18 -> 0.011518015
B26: ARPU (€/Kunde/Monat) | C26: =C18/C6/12 -> 277.75 | D26: =D18/D6/12 -> 304.95 | E26: =E18/E6/12 -> 338.6

Sheet Kosten
B2: Kosten-Projektion
B3: COGS + OPEX nach Kategorie
C5: 2026 | D5: 2027 | E5: 2028
B7: Variable Kosten (COGS)
B8: Engel-Vergütung (Alltagshilfe) | C8: =Umsatz!C9*Annahmen!C18 -> 450000 | D8: =Umsatz!D9*Annahmen!D18 -> 2193750 | E8: =Umsatz!E9*Annahmen!E18 -> 5995080
B9: Fahrer-Vergütung | C9: =Umsatz!C6*Annahmen!C12*Annahmen!C11*12*Annahmen!C21 -> 144000 | D9: =Umsatz!D6*Annahmen!D12*Annahmen!D11*12*Annahmen!D21 -> 725760 | E9: =Umsatz!E6*Annahmen!E12*Annahmen!E11*12*Annahmen!E21 -> 1936872
B10: Pflegeboxen COGS (ProCare) | C10: =Umsatz!C6*Annahmen!C13*12*(Annahmen!C22-Annahmen!C23) -> 36000 | D10: =Umsatz!D6*Annahmen!D13*12*(Annahmen!D22-Annahmen!D23) -> 182250 | E10: =Umsatz!E6*Annahmen!E13*12*(Annahmen!E22-Annahmen!E23) -> 494100
B11: Payment-Processing (1,5 % Umsatz) | C11: =Umsatz!C18*0.015 -> 12498.75 | D11: =Umsatz!D18*0.015 -> 61752.375 | E11: =Umsatz!E18*0.015 -> 167302.26
B12: COGS gesamt | C12: =SUM(C8:C11) -> 642498.75 | D12: =SUM(D8:D11) -> 3163512.4 | E12: =SUM(E8:E11) -> 8593354.3
B14: Bruttogewinn | C14: =Umsatz!C18-C12 -> 190751.25 | D14: =Umsatz!D18-D12 -> 953312.62 | E14: =Umsatz!E18-E12 -> 2560129.7
B15: Bruttomarge | C15: =C14/Umsatz!C18 -> 0.22892439 | D15: =D14/Umsatz!D18 -> 0.23156501 | E15: =E14/Umsatz!E18 -> 0.22953633
B17: Fixkosten (OPEX)
B18: Personal (Gehälter + Lohnnebenkosten) | C18: =Annahmen!C27 -> 480000 | D18: =Annahmen!D27 -> 960000 | E18: =Annahmen!E27 -> 1560000
B19: Marketing & Kundenakquise | C19: =Annahmen!C28 -> 180000 | D19: =Annahmen!D28 -> 420000 | E19: =Annahmen!E28 -> 550000
B20: Infrastruktur & SaaS | C20: =Annahmen!C29 -> 36000 | D20: =Annahmen!D29 -> 72000 | E20: =Annahmen!E29 -> 120000
B21: Recht, Compliance, Versicherung | C21: =Annahmen!C30 -> 72000 | D21: =Annahmen!D30 -> 90000 | E21: =Annahmen!E30 -> 110000
B22: Overhead & Sonstiges | C22: =Annahmen!C31 -> 60000 | D22: =Annahmen!D31 -> 120000 | E22: =Annahmen!E31 -> 180000
B23: OPEX gesamt | C23: =SUM(C18:C22) -> 828000 | D23: =SUM(D18:D22) -> 1662000 | E23: =SUM(E18:E22) -> 2520000
B25: Kosten gesamt (COGS + OPEX) | C25: =C12+C23 -> 1470498.8 | D25: =D12+D23 -> 4825512.4 | E25: =E12+E23 -> 11113354

Sheet P&L
B2: Gewinn- & Verlust-Rechnung
B3: 3-Jahres-Projektion
C5: 2026 | D5: 2027 | E5: 2028
B7: Umsatz
B8: Alltagshilfe §45b | C8: =Umsatz!C13 -> 585000 | D8: =Umsatz!D13 -> 2851875 | E8: =Umsatz!E13 -> 7724430
B9: Krankenfahrten | C9: =Umsatz!C14 -> 192000 | D9: =Umsatz!D14 -> 967680 | E9: =Umsatz!E14 -> 2608848
B10: Pflegeboxen §40 | C10: =Umsatz!C15 -> 50400 | D10: =Umsatz!D15 -> 255150 | E10: =Umsatz!E15 -> 691740
B11: Premium-Abo | C11: =Umsatz!C16 -> 5850 | D11: =Umsatz!D16 -> 42120 | E11: =Umsatz!E16 -> 128466
B12: Umsatz gesamt | C12: =SUM(C8:C11) -> 833250 | D12: =SUM(D8:D11) -> 4116825 | E12: =SUM(E8:E11) -> 11153484
B14: Variable Kosten
B15: COGS | C15: =-Kosten!C12 -> -642498.75 | D15: =-Kosten!D12 -> -3163512.4 | E15: =-Kosten!E12 -> -8593354.3
B16: Bruttogewinn | C16: =C12+C15 -> 190751.25 | D16: =D12+D15 -> 953312.62 | E16: =E12+E15 -> 2560129.7
B17: Bruttomarge % | C17: =C16/C12 -> 0.22892439 | D17: =D16/D12 -> 0.23156501 | E17: =E16/E12 -> 0.22953633
B19: Fixkosten (OPEX)
B20: Personal | C20: =-Annahmen!C27 -> -480000 | D20: =-Annahmen!D27 -> -960000 | E20: =-Annahmen!E27 -> -1560000
B21: Marketing | C21: =-Annahmen!C28 -> -180000 | D21: =-Annahmen!D28 -> -420000 | E21: =-Annahmen!E28 -> -550000
B22: Infrastruktur | C22: =-Annahmen!C29 -> -36000 | D22: =-Annahmen!D29 -> -72000 | E22: =-Annahmen!E29 -> -120000
B23: Recht & Compliance | C23: =-Annahmen!C30 -> -72000 | D23: =-Annahmen!D30 -> -90000 | E23: =-Annahmen!E30 -> -110000
B24: Overhead | C24: =-Annahmen!C31 -> -60000 | D24: =-Annahmen!D31 -> -120000 | E24: =-Annahmen!E31 -> -180000
B25: EBITDA | C25: =C16+SUM(C20:C24) -> -637248.75 | D25: =D16+SUM(D20:D24) -> -708687.38 | E25: =E16+SUM(E20:E24) -> 40129.74
B26: EBITDA-Marge % | C26: =C25/C12 -> -0.76477498 | D26: =D25/D12 -> -0.17214416 | E26: =E25/E12 -> 0.0035979556

Sheet Cashflow
B2: Cashflow-Projektion
B3: Operative, Investive & Finanzierungs-Cashflows
C5: 2026 | D5: 2027 | E5: 2028
B7: Operativer Cashflow
B8: EBITDA | C8: ='P&L'!C25 -> -637248.75 | D8: ='P&L'!D25 -> -708687.38 | E8: ='P&L'!E25 -> 40129.74
B9: Working-Capital-Änderung (Kassen-Payment-Delay) | C9: =-('P&L'!C12-0)*0.05 -> -41662.5 | D9: =-('P&L'!D12-'P&L'!C12)*0.05 -> -164178.75 | E9: =-('P&L'!E12-'P&L'!D12)*0.05 -> -351832.95
B11: Investiver Cashflow
B12: CapEx (Technik, Equipment) | C12: -45000 | D12: -60000 | E12: -80000
B14: Cash-Burn (vor Finanzierung) | C14: =C8+C9+C12 -> -723911.25 | D14: =D8+D9+D12 -> -932866.12 | E14: =E8+E9+E12 -> -391703.21
B16: Finanzierungs-Cashflow
B17: Eigenkapital (Pre-Seed) | C17: 1000000 | D17: 0 | E17: 0
B18: Eigenkapital (Seed-Runde) | C18: 0 | D18: 2500000 | E18: 0
B20: Netto-Cashflow | C20: =C14+C17+C18 -> 276088.75 | D20: =D14+D17+D18 -> 1567133.9 | E20: =E14+E17+E18 -> -391703.21
B22: Kasse (Jahresanfang) | C22: 0 | D22: =C23 -> 276088.75 | E22: =D23 -> 1843222.6
B23: Kasse (Jahresende) | C23: =C22+C20 -> 276088.75 | D23: =D22+D20 -> 1843222.6 | E23: =E22+E20 -> 1451519.4

Sheet Kapital
B2: Kapitalbedarf & Use-of-Funds
B3: Pre-Seed Runde Q2 2026 — 18 Monate Runway
B6: Pre-Seed Runde
B7: Kapitalbedarf | C7: 1000000
B8: Monatlicher Burn-Rate (Ø) | C8: =-(Cashflow!C14)/12 -> 60325.938
B9: Runway (Monate) | C9: =C7/C8 -> 16.576618
B11: Use-of-Funds (1,0 Mio €)
B13: Kategorie | C13: Betrag | D13: Anteil | E13: Zweck
B14: Personal & Team | C14: 400000 | D14: =C14/$C$7 -> 0.4 | E14: 5 Kern-Mitarbeiter (Ops, Sales, Tech) über 18 Monate
B15: Marketing & Kundenakquise | C15: 250000 | D15: =C15/$C$7 -> 0.25 | E15: Performance-Marketing, Content, Ärzte-Empfehlungs-Programm
B16: Tech-Entwicklung & Infrastruktur | C16: 150000 | D16: =C16/$C$7 -> 0.15 | E16: Features, Integrationen, Skalierung, CapEx
B17: City-Launch Köln (Q2'27) | C17: 100000 | D17: =C17/$C$7 -> 0.1 | E17: Lokales Team, Engel-Rekrutierung, Go-to-Market
B18: Regulatorisch & Kassen-Zulassung | C18: 70000 | D18: =C18/$C$7 -> 0.07 | E18: §45a-Antrag NRW, DSGVO-Audits, Legal
B19: Puffer / Unvorhergesehenes | C19: 30000 | D19: =C19/$C$7 -> 0.03 | E19: ~3% Sicherheitspuffer
B21: Summe | C21: =SUM(C14:C20) -> 1000000 | D21: =SUM(D14:D20) -> 1

Sheet Sensitivität
B2: Sensitivitäts-Analyse
B3: Drei Szenarien: Pessimistisch / Base Case / Optimistisch
B5: Szenario | C5: Pessimistisch | D5: Base Case | E5: Optimistisch
B7: Schlüssel-Treiber
B8: Neukunden 2026 | C8: 350 | D8: 500 | E8: 700
B9: Neukunden 2027 | C9: 900 | D9: 1300 | E9: 1700
B10: Neukunden 2028 | C10: 1500 | D10: 2200 | E10: 2900
B11: Churn p.a. | C11: 0.15 | D11: 0.1 | E11: 0.06
B12: Stunden/Kunde/Monat | C12: 4.5 | D12: 6.5 | E12: 7.5
B13: Anteil Fahrtkunden | C13: 0.18 | D13: 0.28 | E13: 0.35
B15: Ergebnis 2028
B16: Umsatz 2028 | C16: =D16*0.55 -> 6134416.2 | D16: =Umsatz!E18 -> 11153484 | E16: =D16*1.45 -> 16172552
B17: EBITDA 2028 | C17: =D17-1800000 -> -1759870.3 | D17: ='P&L'!E25 -> 40129.74 | E17: =D17+2200000 -> 2240129.7
B18: EBITDA-Marge 2028 | C18: =C17/C16 -> -0.28688472 | D18: =D17/D16 -> 0.0035979556 | E18: =E17/E16 -> 0.1385143
B20: Break-Even-Quartal | C20: Q4 2028 | D20: Q2 2028 | E20: Q4 2027
B21: Kapitalbedarf (Seed-Folgerunde) | C21: 4500000 | D21: 2500000 | E21: 1500000
