Workbook

Sheet Revenue Model
A1: REVENUE MODEL PROJECTIONS
A3: ASSUMPTIONS (Input Values)
A5: Commission Rate (%) | B5: 18
A6: Average Booking Value (€) | B6: 35
A7: Average Hours per Booking | B7: 2.5
A8: Sessions per User/Month | B8: 4
A9: Companion Subscription (€/month) | B9: 9.99
A12: REVENUE PROJECTIONS
A14: Metric | B14: Year 1 | C14: Year 2 | D14: Year 3 | E14: Year 4 | F14: Year 5
A15: Active Users | B15: 500 | C15: 2500 | D15: 10000 | E15: 30000 | F15: 75000
A16: Active Companions | B16: 50 | C16: 200 | D16: 800 | E16: 2000 | F16: 5000
A18: Commission Revenue | B18: =B15*$B$8*$B$6*$B$5/100 | C18: =C15*$B$8*$B$6*$B$5/100 | D18: =D15*$B$8*$B$6*$B$5/100 | E18: =E15*$B$8*$B$6*$B$5/100 | F18: =F15*$B$8*$B$6*$B$5/100
A19: Subscription Revenue | B19: =B16*$B$9*12 | C19: =C16*$B$9*12 | D19: =D16*$B$9*12 | E19: =E16*$B$9*12 | F19: =F16*$B$9*12
A20: TOTAL REVENUE | B20: =B18+B19 | C20: =C18+C19 | D20: =D18+D19 | E20: =E18+E19 | F20: =F18+F19

Sheet P&L Summary
A1: PROFIT & LOSS SUMMARY (5-YEAR PROJECTION)
A3: Line Item | B3: Year 1 | C3: Year 2 | D3: Year 3 | E3: Year 4 | F3: Year 5
A4: REVENUE
A5: Commission Revenue | B5: ='Revenue Model'!B18 | C5: ='Revenue Model'!C18 | D5: ='Revenue Model'!D18 | E5: ='Revenue Model'!E18 | F5: ='Revenue Model'!F18
A6: Subscription Revenue | B6: ='Revenue Model'!B19 | C6: ='Revenue Model'!C19 | D6: ='Revenue Model'!D19 | E6: ='Revenue Model'!E19 | F6: ='Revenue Model'!F19
A7: Total Revenue | B7: =B5+B6 | C7: =C5+C6 | D7: =D5+D6 | E7: =E5+E6 | F7: =F5+F6
A9: COST OF GOODS SOLD
A10: Insurance Costs (8% of GMV) | B10: =(B5/$B$5*100)*0.08 | C10: =(C5/$B$5*100)*0.08 | D10: =(D5/$B$5*100)*0.08 | E10: =(E5/$B$5*100)*0.08 | F10: =(F5/$B$5*100)*0.08
A11: Payment Processing (2.5%) | B11: =B7*0.025 | C11: =C7*0.025 | D11: =D7*0.025 | E11: =E7*0.025 | F11: =F7*0.025
A12: Total COGS | B12: =B10+B11 | C12: =C10+C11 | D12: =D10+D11 | E12: =E10+E11 | F12: =F10+F11
A14: GROSS PROFIT | B14: =B7-B12 | C14: =C7-C12 | D14: =D7-D12 | E14: =E7-E12 | F14: =F7-F12
A15: Gross Margin % | B15: =B14/B7 | C15: =C14/C7 | D15: =D14/D7 | E15: =E14/E7 | F15: =F14/F7
A17: OPERATING EXPENSES
A18: Engineering | B18: 150000 | C18: 200000 | D18: 300000 | E18: 400000 | F18: 500000
A19: Marketing & CAC | B19: 100000 | C19: 150000 | D19: 250000 | E19: 400000 | F19: 600000
A20: Operations | B20: 50000 | C20: 80000 | D20: 150000 | E20: 250000 | F20: 400000
A21: General & Administrative | B21: 50000 | C21: 75000 | D21: 120000 | E21: 180000 | F21: 250000
A22: Total OpEx | B22: =B18+B19+B20+B21 | C22: =C18+C19+C20+C21 | D22: =D18+D19+D20+D21 | E22: =E18+E19+E20+E21 | F22: =F18+F19+F20+F21
A24: EBITDA | B24: =B14-B22 | C24: =C14-C22 | D24: =D14-D22 | E24: =E14-E22 | F24: =F14-F22

Sheet Key Metrics
A1: KEY METRICS & KPIs (5-YEAR PROJECTION)
A3: Metric | B3: Year 1 | C3: Year 2 | D3: Year 3 | E3: Year 4 | F3: Year 5
A4: VOLUME METRICS
A5: Gross Merchandise Value (GMV) | B5: ='P&L Summary'!B5/$B$5*100 | C5: ='P&L Summary'!C5/$B$5*100 | D5: ='P&L Summary'!D5/$B$5*100 | E5: ='P&L Summary'!E5/$B$5*100 | F5: ='P&L Summary'!F5/$B$5*100
A6: Take Rate | B6: $B$5 | C6: $B$5 | D6: $B$5 | E6: $B$5 | F6: $B$5
A7: Active Users | B7: ='Revenue Model'!B15 | C7: ='Revenue Model'!C15 | D7: ='Revenue Model'!D15 | E7: ='Revenue Model'!E15 | F7: ='Revenue Model'!F15
A8: Active Companions | B8: ='Revenue Model'!B16 | C8: ='Revenue Model'!C16 | D8: ='Revenue Model'!D16 | E8: ='Revenue Model'!E16 | F8: ='Revenue Model'!F16
A10: REVENUE METRICS
A11: Revenue per User (Annual) | B11: ='P&L Summary'!B7/B7 | C11: ='P&L Summary'!C7/C7 | D11: ='P&L Summary'!D7/D7 | E11: ='P&L Summary'!E7/E7 | F11: ='P&L Summary'!F7/F7
A12: Revenue per Companion (Annual) | B12: ='P&L Summary'!B6/B8 | C12: ='P&L Summary'!C6/C8 | D12: ='P&L Summary'!D6/D8 | E12: ='P&L Summary'!E6/E8 | F12: ='P&L Summary'!F6/F8
A13: Customer Acquisition Cost (CAC) | B13: 200 | C13: 75 | D13: 33.333333 | E13: 20 | F13: 13.333333
A14: Customer Lifetime Value (LTV) | B14: =B11/3 | C14: =C11/3 | D14: =D11/3 | E14: =E11/3 | F14: =F11/3
A15: LTV / CAC Ratio | B15: =B14/B13 | C15: =C14/C13 | D15: =D14/D13 | E15: =E14/E13 | F15: =F14/F13
A17: GROWTH METRICS
A18: Monthly Active Users Growth Rate | B18: =(B15-500)/500 | C18: =(C15-B15)/B15 | D18: =(D15-C15)/C15 | E18: =(E15-D15)/D15 | F18: =(F15-E15)/E15
A19: Companion Utilization Rate | B19: 0.8 | C19: 0.82 | D19: 0.84 | E19: 0.85 | F19: 0.85
